michelson_kernel/README.md
michelson_kernel/__init__.py
michelson_kernel/__main__.py
michelson_kernel/cli.py
michelson_kernel/docs.py
michelson_kernel/kernel.js
michelson_kernel/kernel.py
pytezos/__init__.py
pytezos/__main__.py
pytezos/block/__init__.py
pytezos/block/forge.py
pytezos/block/header.py
pytezos/cli/__init__.py
pytezos/cli/__main__.py
pytezos/cli/cli.py
pytezos/cli/github.py
pytezos/client.py
pytezos/context/__init__.py
pytezos/context/abstract.py
pytezos/context/impl.py
pytezos/context/mixin.py
pytezos/contract/__init__.py
pytezos/contract/call.py
pytezos/contract/data.py
pytezos/contract/entrypoint.py
pytezos/contract/interface.py
pytezos/contract/metadata-schema.json
pytezos/contract/metadata.py
pytezos/contract/result.py
pytezos/contract/token_metadata-schema.json
pytezos/contract/token_metadata.py
pytezos/contract/view.py
pytezos/crypto/__init__.py
pytezos/crypto/encoding.py
pytezos/crypto/hash.py
pytezos/crypto/keccak.py
pytezos/crypto/key.py
pytezos/jupyter.py
pytezos/logging.py
pytezos/michelson/__init__.py
pytezos/michelson/forge.py
pytezos/michelson/format.py
pytezos/michelson/instructions/__init__.py
pytezos/michelson/instructions/adt.py
pytezos/michelson/instructions/arithmetic.py
pytezos/michelson/instructions/base.py
pytezos/michelson/instructions/boolean.py
pytezos/michelson/instructions/compare.py
pytezos/michelson/instructions/control.py
pytezos/michelson/instructions/crypto.py
pytezos/michelson/instructions/generic.py
pytezos/michelson/instructions/jupyter.py
pytezos/michelson/instructions/stack.py
pytezos/michelson/instructions/struct.py
pytezos/michelson/instructions/tezos.py
pytezos/michelson/instructions/ticket.py
pytezos/michelson/instructions/tzt.py
pytezos/michelson/macros.py
pytezos/michelson/micheline.py
pytezos/michelson/parse.py
pytezos/michelson/program.py
pytezos/michelson/repl.py
pytezos/michelson/sections/__init__.py
pytezos/michelson/sections/code.py
pytezos/michelson/sections/parameter.py
pytezos-3.16.0.dist-info/METADATA
pytezos-3.16.0.dist-info/WHEEL
pytezos-3.16.0.dist-info/entry_points.txt
pytezos-3.16.0.dist-info/licenses/LICENSE
pytezos-3.16.0.dist-info/RECORD
