Metadata-Version: 2.4
Name: pytezos
Version: 3.16.0
Summary: Python toolkit for Tezos
License: MIT
License-File: LICENSE
Keywords: tezos,blockchain,sdk,michelson,repl,cryptocurrencies,smart-contracts,jupyter,ipython,docker,crypto
Author: Michael Zaikin
Author-email: mz@baking-bad.org
Maintainer: Lev Gorodetskii
Maintainer-email: pytezos@drsr.io
Requires-Python: >=3.9,<3.14
Classifier: Development Status :: 5 - Production/Stable
Classifier: Environment :: Console
Classifier: Framework :: IPython
Classifier: Intended Audience :: Developers
Classifier: License :: OSI Approved :: MIT License
Classifier: Operating System :: OS Independent
Classifier: Programming Language :: Python :: 3
Classifier: Programming Language :: Python :: 3.9
Classifier: Programming Language :: Python :: 3.10
Classifier: Programming Language :: Python :: 3.11
Classifier: Programming Language :: Python :: 3.12
Classifier: Programming Language :: Python :: 3.13
Classifier: Programming Language :: Python :: Implementation :: CPython
Classifier: Topic :: Software Development :: Libraries :: Application Frameworks
Classifier: Typing :: Typed
Requires-Dist: attrs (>=21.4.0)
Requires-Dist: base58 (>=2.1.1)
Requires-Dist: cattrs (>=22.1.0)
Requires-Dist: click (>=8.1.3)
Requires-Dist: coincurve (>=20.0.0)
Requires-Dist: cryptography (>=42.0.4)
Requires-Dist: deprecation (>=2.1.0)
Requires-Dist: docker (>=6.0.0)
Requires-Dist: fastecdsa (>=2.2.3)
Requires-Dist: jsonschema (>=4.3.2)
Requires-Dist: mnemonic (>=0.21)
Requires-Dist: netstruct (>=1.1.2)
Requires-Dist: notebook (>=6.5,<7)
Requires-Dist: ply (>=3.11)
Requires-Dist: py-ecc (==7.0.1)
Requires-Dist: pysodium (>=0.7.10)
Requires-Dist: python-dateutil (>=2.8.2)
Requires-Dist: requests (>=2.28.2)
Requires-Dist: simple-bson (>=0.0.3)
Requires-Dist: simplejson (>=3.17.6)
Requires-Dist: strict-rfc3339 (>=0.7)
Requires-Dist: tabulate (>=0.9.0)
Requires-Dist: testcontainers (>=3.7.0)
Requires-Dist: tqdm (>=4.62.3)
Project-URL: Homepage, https://pytezos.org
Project-URL: Repository, https://github.com/baking-bad/pytezos
